inventree_brother_label/__init__.py
inventree_brother_label/brother_label_plugin.py
inventree_brother_label/version.py
inventree_brother_label_plugin-2.0a11.dist-info/LICENSE
inventree_brother_label_plugin-2.0a11.dist-info/METADATA
inventree_brother_label_plugin-2.0a11.dist-info/WHEEL
inventree_brother_label_plugin-2.0a11.dist-info/entry_points.txt
inventree_brother_label_plugin-2.0a11.dist-info/top_level.txt
inventree_brother_label_plugin-2.0a11.dist-info/RECORD
