Metadata-Version: 2.1
Name: inventree-brother-label-plugin
Version: 2.0a11
Summary: Brother label printer plugin for InvenTree
Home-page: https://github.com/fuzeman/inventree-brother-label-plugin
Author: Dean Gardiner
Author-email: me@dgardiner.net
License: MIT
Keywords: inventree label printer printing inventory
Requires-Python: >=3.9
License-File: LICENSE
Requires-Dist: brother-label>=2.0a8
